LICENSE
MANIFEST.in
README.md
setup.py
themesaver/TakeScreenshot.sh
themesaver/__init__.py
themesaver/config.env
themesaver/themesaver.py
themesaver.egg-info/PKG-INFO
themesaver.egg-info/SOURCES.txt
themesaver.egg-info/dependency_links.txt
themesaver.egg-info/entry_points.txt
themesaver.egg-info/requires.txt
themesaver.egg-info/top_level.txt
themesaver/Cli/__init__.py
themesaver/Cli/deleteSlot.py
themesaver/Cli/exportSlot.py
themesaver/Cli/importSlot.py
themesaver/Cli/listSlots.py
themesaver/Cli/loadSlot.py
themesaver/Cli/saveSlot.py
themesaver/Cli/__pycache__/__init__.cpython-310.pyc
themesaver/Cli/__pycache__/deleteSlot.cpython-310.pyc
themesaver/Cli/__pycache__/exportSlot.cpython-310.pyc
themesaver/Cli/__pycache__/importSlot.cpython-310.pyc
themesaver/Cli/__pycache__/listSlots.cpython-310.pyc
themesaver/Cli/__pycache__/loadSlot.cpython-310.pyc
themesaver/Cli/__pycache__/saveSlot.cpython-310.pyc
themesaver/DesktopEnvironments/__init__.py
themesaver/DesktopEnvironments/gnome.py
themesaver/DesktopEnvironments/kde.py
themesaver/DesktopEnvironments/lxde.py
themesaver/DesktopEnvironments/xfce.py
themesaver/DesktopEnvironments/__pycache__/qtile.cpython-310.pyc
themesaver/GUI/ImportSlotWindow.py
themesaver/GUI/LoadSlotWindow.py
themesaver/GUI/LoadingAnimation.py
themesaver/GUI/LoadingWindow.py
themesaver/GUI/MainWindow.py
themesaver/GUI/SaveSlotWindow.py
themesaver/GUI/ShopWindow.py
themesaver/GUI/__init__.py
themesaver/GUI/Design/ImportWindow.ui
themesaver/GUI/Design/LoadSlotWindow.ui
themesaver/GUI/Design/LoadingWindow.ui
themesaver/GUI/Design/MainWindow.ui
themesaver/GUI/Design/SaveSlotWindow.ui
themesaver/GUI/Design/ShopWindow.ui
themesaver/GUI/Icons/icon-pack
themesaver/GUI/Icons/Dracula/BackArrow.png
themesaver/GUI/Icons/Dracula/Confirm.png
themesaver/GUI/Icons/Dracula/Delete.png
themesaver/GUI/Icons/Dracula/Export.png
themesaver/GUI/Icons/Dracula/Exporting.gif
themesaver/GUI/Icons/Dracula/ForwardArrow.png
themesaver/GUI/Icons/Dracula/Import.png
themesaver/GUI/Icons/Dracula/Importing.gif
themesaver/GUI/Icons/Dracula/LoadSlot.png
themesaver/GUI/Icons/Dracula/Save.png
themesaver/GUI/Icons/Dracula/SaverText.png
themesaver/GUI/Icons/Dracula/Settings.png
