Metadata-Version: 2.1
Name: themesaver
Version: 1.2.3
Summary: A python script to manage your rices
Home-page: https://github.com/techcoder20/themesaver
Author: RPICoder
Author-email: rpicoder@protonmail.com
License: GPLV3
Platform: UNKNOWN
License-File: LICENSE
